{
	"textures": [
		{
			"image": "walls.png",
			"format": "RGBA8888",
			"size": {
				"w": 128,
				"h": 96
			},
			"scale": 1,
			"frames": [
				{
					"filename": "StreetSign_4_0.png",
					"rotated": false,
					"trimmed": false,
					"sourceSize": {
						"w": 128,
						"h": 96
					},
					"spriteSourceSize": {
						"x": 0,
						"y": 0,
						"w": 128,
						"h": 96
					},
					"frame": {
						"x": 0,
						"y": 0,
						"w": 128,
						"h": 96
					}
				}
			]
		}
	],
	"meta": {
		"app": "https://www.codeandweb.com/texturepacker",
		"version": "3.0",
		"smartupdate": "$TexturePacker:SmartUpdate:7587e193ed6e353515e0f7b6619f3a48:8247975e64eb31371f62bc4afdf9ce08:5c2f5c663ae0680c530bc1f885567038$"
	}
}
